afterpython/__init__.py
afterpython/_io/toml.py
afterpython/_io/yaml.py
afterpython/_paths.py
afterpython/_typing.py
afterpython/builders/__init__.py
afterpython/builders/content_json.py
afterpython/builders/index_md.py
afterpython/builders/jupyter_notebook.py
afterpython/builders/markdown.py
afterpython/builders/metadata.py
afterpython/cli/__init__.py
afterpython/cli/commands/add.py
afterpython/cli/commands/build.py
afterpython/cli/commands/bump.py
afterpython/cli/commands/check.py
afterpython/cli/commands/clean.py
afterpython/cli/commands/commit.py
afterpython/cli/commands/commitizen.py
afterpython/cli/commands/dev.py
afterpython/cli/commands/format.py
afterpython/cli/commands/init.py
afterpython/cli/commands/init_branch_rules.py
afterpython/cli/commands/install.py
afterpython/cli/commands/lock.py
afterpython/cli/commands/pre_commit.py
afterpython/cli/commands/preview.py
afterpython/cli/commands/release.py
afterpython/cli/commands/remove.py
afterpython/cli/commands/start.py
afterpython/cli/commands/sync.py
afterpython/cli/commands/update.py
afterpython/cli/main.py
afterpython/const.py
afterpython/main.py
afterpython/pcu.py
afterpython/templates/ci-workflow-template.yml
afterpython/templates/cz-template.toml
afterpython/templates/dependabot-template.yml
afterpython/templates/deploy-workflow-template.yml
afterpython/templates/pre-commit-config-template.yaml
afterpython/templates/release-workflow-template.yml
afterpython/templates/ruff-template.toml
afterpython/tools/_afterpython.py
afterpython/tools/_git.py
afterpython/tools/branch_rules.py
afterpython/tools/commitizen.py
afterpython/tools/github_actions.py
afterpython/tools/myst.py
afterpython/tools/pre_commit.py
afterpython/tools/pyproject.py
afterpython/utils.py
afterpython/version.py
afterpython-0.1.1.dist-info/WHEEL
afterpython-0.1.1.dist-info/entry_points.txt
afterpython-0.1.1.dist-info/METADATA
afterpython-0.1.1.dist-info/RECORD
