Metadata-Version: 2.4
Name: afterpython
Version: 0.1.1
Summary: CLI tool to streamline Python package maintenance and generate a dedicated project website
Keywords: package-maintenance,project-website,static-site-generator,developer-tools,documentation,cli-tool,ci/cd,mystmd,semantic-release,python-packaging
Author: Stephen Yau
Author-email: Stephen Yau <softwareentrepreneer+afterpython@gmail.com>
License-Expression: Apache-2.0
Classifier: Operating System :: OS Independent
Classifier: Intended Audience :: Developers
Classifier: Topic :: Software Development :: Build Tools
Classifier: Topic :: Software Development :: Documentation
Classifier: Typing :: Typed
Classifier: Programming Language :: Python :: 3.11
Classifier: Programming Language :: Python :: 3.12
Classifier: Programming Language :: Python :: 3.13
Requires-Dist: click>=8.3.1
Requires-Dist: trogon>=0.6.0
Requires-Dist: httpx>=0.28.1
Requires-Dist: tomlkit>=0.13.3
Requires-Dist: ruamel-yaml>=0.18.16
Requires-Dist: gitpython>=3.1.45
Requires-Dist: python-dotenv>=1.2.1
Requires-Dist: pyproject-metadata>=0.10.0
Requires-Dist: mystmd>=1.7.0
Requires-Dist: pdoc>=16.0.0
Requires-Dist: ruff>=0.14.8
Requires-Dist: pre-commit>=4.5.0
Requires-Dist: commitizen>=4.10.0
Requires-Python: >=3.11
Project-URL: documentation, https://afterpython.afterpython.org/doc
Project-URL: homepage, https://afterpython.afterpython.org
Project-URL: repository, https://github.com/AfterPythonOrg/afterpython
